arag/__init__.py
arag/arag.py
arag/globals.py
arag-0.1.0.dist-info/LICENSE
arag-0.1.0.dist-info/METADATA
arag-0.1.0.dist-info/WHEEL
arag-0.1.0.dist-info/entry_points.txt
arag-0.1.0.dist-info/top_level.txt
arag-0.1.0.dist-info/RECORD
