Metadata-Version: 2.2
Name: arag
Version: 0.1.0
Summary: A CLI tool for creating, managing, and querying .arag files for RAG applications
Home-page: https://github.com/jmelovich/arag-cli
Author: John Luke Melovich
Author-email: John Luke Melovich <lmelovich@outlook.com>
License: MIT License
Project-URL: Homepage, https://github.com/jmelovich/arag-cli
Project-URL: Repository, https://github.com/jmelovich/arag-cli.git
Keywords: rag,embeddings,cli,vector-search,document-processing
Classifier: Development Status :: 4 - Beta
Classifier: Environment :: Console
Classifier: Intended Audience :: Developers
Classifier: License :: OSI Approved :: MIT License
Classifier: Operating System :: OS Independent
Classifier: Programming Language :: Python :: 3
Classifier: Programming Language :: Python :: 3.10
Classifier: Topic :: Software Development :: Libraries :: Python Modules
Classifier: Topic :: Text Processing :: General
Requires-Python: >=3.10
License-File: LICENSE
Requires-Dist: apsw
Requires-Dist: numpy
Requires-Dist: openai
Requires-Dist: pypdf
Requires-Dist: Spire.Doc
Provides-Extra: local-embeddings
Requires-Dist: sentence-transformers; extra == "local-embeddings"
Dynamic: author
Dynamic: home-page
Dynamic: requires-python
